avibe/__init__.py
avibe/avibe.py
avibe-0.3.0.dist-info/licenses/LICENSE
tests/__init__.py
tests/test_notebook_execution.py
tests/test_run_asnc_function.py
avibe-0.3.0.dist-info/METADATA
avibe-0.3.0.dist-info/WHEEL
avibe-0.3.0.dist-info/top_level.txt
avibe-0.3.0.dist-info/RECORD
