Metadata-Version: 2.4
Name: avibe
Version: 0.3.0
Summary: Utility for executing python async functions everywhere the same way - scripts, notebooks, etc.
Home-page: https://github.com/zach-blumenfeld/avibe
Author: Zach Blumenfeld
Author-email: zblumenf@gmail.com
License: Apache 2.0
Classifier: Programming Language :: Python :: 3
Classifier: Programming Language :: Python :: 3.6
Classifier: License :: OSI Approved :: Apache Software License
Classifier: Operating System :: OS Independent
Requires-Python: >=3.6
License-File: LICENSE
Requires-Dist: nest-asyncio
Provides-Extra: test
Requires-Dist: unittest; extra == "test"
Requires-Dist: nbconvert; extra == "test"
Requires-Dist: nbformat; extra == "test"
Requires-Dist: jupyter; extra == "test"
Requires-Dist: pytest; extra == "test"
Dynamic: author
Dynamic: author-email
Dynamic: classifier
Dynamic: description
Dynamic: description-content-type
Dynamic: home-page
Dynamic: license
Dynamic: license-file
Dynamic: provides-extra
Dynamic: requires-dist
Dynamic: requires-python
Dynamic: summary
